myapp/__init__.py
myapp/admin.py
myapp/apps.py
myapp/models.py
myapp/serializer.py
myapp/tests.py
myapp/urls.py
myapp/views.py
MyAppModules-1.0.dist-info/METADATA
MyAppModules-1.0.dist-info/WHEEL
MyAppModules-1.0.dist-info/top_level.txt
MyAppModules-1.0.dist-info/RECORD
